icartt/__init__.py
icartt/dataset.py
icartt/utils.py
icartt-2.0.0.dist-info/LICENSE
icartt-2.0.0.dist-info/WHEEL
icartt-2.0.0.dist-info/METADATA
icartt-2.0.0.dist-info/RECORD
