Metadata-Version: 2.1
Name: icartt
Version: 2.0.0
Summary: ICARTT format reader and writer
Home-page: https://mbees.med.uni-augsburg.de/
License: GPL-3.0-or-later
Keywords: atmosphere,file format,ames,nasa
Author: Christoph Knote
Author-email: christoph.knote@med.uni-augsburg.de
Requires-Python: >=3.7,<4
Classifier: Development Status :: 5 - Production/Stable
Classifier: Environment :: Console
Classifier: Intended Audience :: Developers
Classifier: Intended Audience :: Education
Classifier: Intended Audience :: End Users/Desktop
Classifier: Intended Audience :: Science/Research
Classifier: License :: OSI Approved :: GNU General Public License v3 or later (GPLv3+)
Classifier: Operating System :: POSIX
Classifier: Programming Language :: Python :: 3
Classifier: Programming Language :: Python :: 3.10
Classifier: Programming Language :: Python :: 3.7
Classifier: Programming Language :: Python :: 3.8
Classifier: Programming Language :: Python :: 3.9
Classifier: Topic :: Education
Classifier: Topic :: Scientific/Engineering
Classifier: Topic :: Utilities
Requires-Dist: numpy (>=1.19)
Project-URL: Bug Tracker, http://mbees.med.uni-augsburg.de/gitlab/mbees/icartt_pypackage/issues
Project-URL: Documentation, https://mbees.med.uni-augsburg.de/docs/icartt/2.0.0/
Project-URL: Repository, https://mbees.med.uni-augsburg.de/gitlab/mbees/icartt_pypackage
